PyPIMetaMorphosis/__init__.py
PyPIMetaMorphosis/src/PyPIMetaMorphosis.py
PyPIMetaMorphosis/src/__init__.py
PyPIMetaMorphosis/test/__init__.py
PyPIMetaMorphosis/test/test_PyPIMetaMorphosis.py
PyPIMetaMorphosis-1.0.4.dist-info/LICENSE
PyPIMetaMorphosis-1.0.4.dist-info/METADATA
PyPIMetaMorphosis-1.0.4.dist-info/WHEEL
PyPIMetaMorphosis-1.0.4.dist-info/top_level.txt
PyPIMetaMorphosis-1.0.4.dist-info/RECORD
