Metadata-Version: 2.1
Name: PyPIMetaMorphosis
Version: 1.0.4
Summary: Create a ready-to-publish PyPI project structure with the given project name, author name, author email, and project description.
Home-page: https://github.com/Hardvan/PyPIMetaMorphosis
Author: Hardik Pawar
Author-email: hardikpawarh@gmail.com
License: UNKNOWN
Keywords: automation,pypi,template,project,structure,skeleton,repository
Platform: UNKNOWN
Classifier: Programming Language :: Python :: 3
Classifier: License :: OSI Approved :: MIT License
Classifier: Operating System :: OS Independent
Requires-Python: >=3.6
License-File: LICENSE
